inferless/__init__.py
inferless/api.py
inferless/auth/__init__.py
inferless/auth/token.py
inferless/rpc/__init__.py
inferless/rpc/config_yaml.py
inferless/rpc/rpc.py
inferless/utils/__init__.py
inferless/utils/inputs.py
inferless/utils/zip_working_dir.py
inferless-0.2.15.dist-info/METADATA
inferless-0.2.15.dist-info/WHEEL
inferless-0.2.15.dist-info/RECORD
